hack4u/__init__.py
hack4u/courses.py
hack4u/utils.py
my_first_project_jhonny_navarrete-0.1.0.dist-info/METADATA
my_first_project_jhonny_navarrete-0.1.0.dist-info/WHEEL
my_first_project_jhonny_navarrete-0.1.0.dist-info/top_level.txt
my_first_project_jhonny_navarrete-0.1.0.dist-info/RECORD
