Metadata-Version: 2.4
Name: my_first_project_jhonny_navarrete
Version: 0.1.0
Summary: Una biblioteca para consultar cursos de hack4u
Home-page: https://google.com
Author: Jhonny Navarrete
Dynamic: author
Dynamic: description
Dynamic: description-content-type
Dynamic: home-page
Dynamic: summary
